configsuite_tui/__about__.py
configsuite_tui/__init__.py
configsuite_tui/__main__.py
configsuite_tui/_version.py
configsuite_tui/config_tools.py
configsuite_tui/custom_widgets.py
configsuite_tui/hookspecs.py
configsuite_tui/test_hook_dict.py
configsuite_tui/test_hook_list.py
configsuite_tui/test_hook_named_dict.py
configsuite_tui/tui.py
configsuite_tui-0.2.3.dist-info/LICENSE
configsuite_tui-0.2.3.dist-info/METADATA
configsuite_tui-0.2.3.dist-info/WHEEL
configsuite_tui-0.2.3.dist-info/entry_points.txt
configsuite_tui-0.2.3.dist-info/top_level.txt
configsuite_tui-0.2.3.dist-info/RECORD
