Metadata-Version: 2.1
Name: configsuite-tui
Version: 0.2.3
Summary: Text-based user interface for Config Suite
Home-page: https://github.com/equinor/configsuite-tui
Author: Equinor ASA
License: MIT
Platform: UNKNOWN
Requires-Python: >=3.6
Requires-Dist: pyyaml
Requires-Dist: npyscreen
Requires-Dist: configsuite
Requires-Dist: fastnumbers
Requires-Dist: pluggy
Requires-Dist: python-dateutil
